README.md
setup.py
stat_probability/Binomialdistribution.py
stat_probability/Gaussiandistribution.py
stat_probability/Generaldistribution.py
stat_probability/__init__.py
stat_probability.egg-info/PKG-INFO
stat_probability.egg-info/SOURCES.txt
stat_probability.egg-info/dependency_links.txt
stat_probability.egg-info/not-zip-safe
stat_probability.egg-info/top_level.txt