Metadata-Version: 1.0
Name: stat-probability
Version: 0.5
Summary: Gaussian and Binomial distribution.
Home-page: UNKNOWN
Author: Aniket Hande
Author-email: anikethande779@gmail.com
License: MIT
Platform: UNKNOWN
